
<ReorgSpec>
<SpecVersion>18_0_10-184260</SpecVersion>
<Table>
<TableId>8</TableId>
<TableName>Catalogo</TableName>
<Description>Catalogo</Description></Table>
<ReorgCls>c</ReorgCls>
<ReorgCode>same</ReorgCode>
<ReorgMsg>Catalogo needs conversion</ReorgMsg>
<ReorgAction>#</ReorgAction>
<TableAttributes>
<AttrisInTable>
<Attribute>
<AttriId>28</AttriId>
<AttriName>CatalogoID</AttriName>
<Description>Catalogo ID</Description>
<TakesValueFrom></TakesValueFrom>
<OnPrimaryKey>Yes</OnPrimaryKey>
<AttriType>
<DataType>N</DataType>
<Presicion>6</Presicion>
<Scale>0</Scale>
<Properties>
<Property>
<Name>Autonumber</Name>
<Value>Yes</Value></Property>
<Property>
<Name>Autogenerate</Name>
<Value>No</Value></Property>
<Property>
<Name>AllowNulls</Name>
<Value>No</Value></Property></Properties></AttriType></Attribute>
<Attribute>
<AttriId>29</AttriId>
<AttriName>CatalogoDescripcion</AttriName>
<Description>Catalogo Descripcion</Description>
<TakesValueFrom></TakesValueFrom>
<AttriType>
<DataType>V</DataType>
<Presicion>80</Presicion>
<Scale>0</Scale>
<Properties>
<Property>
<Name>Autonumber</Name>
<Value>No</Value></Property>
<Property>
<Name>Autogenerate</Name>
<Value>No</Value></Property>
<Property>
<Name>AllowNulls</Name>
<Value>No</Value></Property>
<Property>
<Name>NLS</Name>
<Value>Yes</Value></Property></Properties></AttriType></Attribute>
<Attribute>
<AttriId>30</AttriId>
<AttriName>CatalogoImagen</AttriName>
<Description>Catalogo Imagen</Description>
<TakesValueFrom></TakesValueFrom>
<AttriType>
<DataType>B</DataType>
<Presicion>1024</Presicion>
<Scale>0</Scale>
<Properties>
<Property>
<Name>Autonumber</Name>
<Value>No</Value></Property>
<Property>
<Name>Autogenerate</Name>
<Value>No</Value></Property>
<Property>
<Name>AllowNulls</Name>
<Value>No</Value></Property></Properties></AttriType></Attribute>
<Attribute>
<AttriId>40000</AttriId>
<AttriName>CatalogoImagen_GXI</AttriName>
<Description>CatalogoImagen_GXI</Description>
<TakesValueFrom></TakesValueFrom>
<AttriType>
<DataType>V</DataType>
<Presicion>2048</Presicion>
<Scale>0</Scale>
<Properties>
<Property>
<Name>Autonumber</Name>
<Value>No</Value></Property>
<Property>
<Name>Autogenerate</Name>
<Value>No</Value></Property>
<Property>
<Name>AllowNulls</Name>
<Value>No</Value></Property></Properties></AttriType></Attribute>
<Attribute>
<AttriId>31</AttriId>
<AttriName>CatalogoFchInicio</AttriName>
<Description>Catalogo Fch Inicio</Description>
<TakesValueFrom></TakesValueFrom>
<AttriType>
<DataType>D</DataType>
<Presicion>8</Presicion>
<Scale>0</Scale>
<Properties>
<Property>
<Name>Autonumber</Name>
<Value>No</Value></Property>
<Property>
<Name>Autogenerate</Name>
<Value>No</Value></Property>
<Property>
<Name>AllowNulls</Name>
<Value>No</Value></Property></Properties></AttriType></Attribute>
<Attribute>
<AttriId>32</AttriId>
<AttriName>CatalogoFchFin</AttriName>
<Description>Catalogo Fch Fin</Description>
<TakesValueFrom></TakesValueFrom>
<AttriType>
<DataType>D</DataType>
<Presicion>8</Presicion>
<Scale>0</Scale>
<Properties>
<Property>
<Name>Autonumber</Name>
<Value>No</Value></Property>
<Property>
<Name>Autogenerate</Name>
<Value>No</Value></Property>
<Property>
<Name>AllowNulls</Name>
<Value>No</Value></Property></Properties></AttriType></Attribute></AttrisInTable>
<AttrisNoLongerInTable></AttrisNoLongerInTable>
<AttrisInManyTables></AttrisInManyTables></TableAttributes>
<TableIndices>
<Indices>
<Index>
<IndexName>ICATALOGO</IndexName>
<IndexType>u</IndexType>
<IndexAttris>
<Attribute>
<AttriId>28</AttriId>
<AttriName>CatalogoID</AttriName>
<Description>Catalogo ID</Description></Attribute></IndexAttris>
<IndexExistance>AlreadyExist</IndexExistance>
<Clustered>Yes</Clustered></Index></Indices>
<NewIndices>
<Index>
<IndexName>UCATALOGO</IndexName>
<IndexType>d</IndexType>
<IndexAttris>
<Attribute>
<AttriId>29</AttriId>
<AttriName>CatalogoDescripcion</AttriName>
<Description>Catalogo Descripcion</Description></Attribute></IndexAttris>
<IndexExistance>AlreadyExist</IndexExistance>
<Clustered>No</Clustered></Index></NewIndices></TableIndices>
<FKConstraints></FKConstraints>
<Statements>
<Statement>CREATE NONCLUSTERED INDEX [UCATALOGO] ON [Catalogo] ([CatalogoDescripcion] )</Statement></Statements>
<NeedReorganizationProgram>False</NeedReorganizationProgram>
<Warnings></Warnings>
<Errors></Errors></ReorgSpec>